{
  "required": true,
  "minVersion": "0.8",
  "package": "com.pixulse.infx.mixin",
  "mixins": [
    "AbstractContainerMenuMixin",
    "AbstractFurnaceBlockEntityMixin",
    "CakeBlockMixin",
    "ChunkGeneratorMixin",
    "CraftingMenuMixin",
    "DifficultyInvoker",
    "DifficultyMixin",
    "EggItemMixin",
    "EnchantmentMenuAccessor",
    "FishingHookMixin",
    "FurnaceFuelSlotMixin",
    "FurnaceInputSlotMixin",
    "FoodDataMixin",
    "GameTestServerMixin",
    "InventoryMenuMixin",
    "LavaFluidMixin",
    "HopperBlockEntityMixin",
    "PlayerExperienceMixin",
    "PlayerAttackRangeMixin",
    "PlayerFoodMixin",
    "RaidMixin"
  ],
  "client": [
    "DebugScreenOverlayMixin",
    "MinecraftMiningInputMixin"
  ],
  "injectors": {
    "defaultRequire": 1
  },
  "overwrites": {
    "requireAnnotations": true
  }
}
